mitel_ommclient2/__init__.py
mitel_ommclient2/cli.py
mitel_ommclient2/client.py
mitel_ommclient2/connection.py
mitel_ommclient2/exceptions.py
mitel_ommclient2/messages/__init__.py
mitel_ommclient2/messages/createppuser.py
mitel_ommclient2/messages/getaccount.py
mitel_ommclient2/messages/getppdev.py
mitel_ommclient2/messages/getppuser.py
mitel_ommclient2/messages/getpublickey.py
mitel_ommclient2/messages/open.py
mitel_ommclient2/messages/ping.py
mitel_ommclient2/messages/setpp.py
mitel_ommclient2/messages/setppuser.py
mitel_ommclient2/messages/setppuserdevrelation.py
mitel_ommclient2/types/__init__.py
mitel_ommclient2-0.0.1.dist-info/METADATA
mitel_ommclient2-0.0.1.dist-info/WHEEL
mitel_ommclient2-0.0.1.dist-info/entry_points.txt
mitel_ommclient2-0.0.1.dist-info/license_files/LICENSE
mitel_ommclient2-0.0.1.dist-info/RECORD
