Metadata-Version: 2.1
Name: mitel-ommclient2
Version: 0.0.1
Summary: Another attempt for a modern client library to the Mitel OM Application XML Interface.
Project-URL: Source, https://git.clerie.de/clerie/mitel_ommclient2
Author-email: clerie <hallo@clerie.de>
License: MIT License
Classifier: License :: OSI Approved :: MIT License
Classifier: Operating System :: OS Independent
Classifier: Programming Language :: Python :: 3
Requires-Python: >=3.7
Provides-Extra: crypt
Requires-Dist: rsa; extra == 'crypt'
